[
  {
    "rank": 1,
    "name": "JACKBOYS",
    "country": "la"
  },
  {
    "rank": 2,
    "name": "jikroy",
    "team_id": 9829573,
    "team_tag": "RKX",
    "country": "ps"
  },
  {
    "rank": 3,
    "name": "Pota2",
    "team_id": 9865903,
    "team_tag": "VRJ"
  },
  {
    "rank": 4,
    "name": "Aq",
    "team_id": 8021080,
    "team_tag": ""
  },
  {
    "rank": 5,
    "name": "Xm",
    "team_id": 726228,
    "team_tag": "VG",
    "country": "cn"
  },
  {
    "rank": 6,
    "name": "Abed",
    "team_id": 9895392,
    "team_tag": "VP",
    "country": "af"
  },
  {
    "rank": 7,
    "name": "Mireska"
  },
  {
    "rank": 8,
    "name": "zeal",
    "country": "my"
  },
  {
    "rank": 9,
    "name": "Ghost",
    "country": "my"
  },
  {
    "rank": 10,
    "name": "无限",
    "team_id": 10007878,
    "team_tag": "",
    "country": "cn"
  },
  {
    "rank": 11,
    "name": "inYourdreaM",
    "team_id": 9828897,
    "team_tag": "RKX"
  },
  {
    "rank": 11,
    "name": "Armel"
  },
  {
    "rank": 13,
    "name": "Young PH"
  },
  {
    "rank": 14,
    "name": "Ksh"
  },
  {
    "rank": 15,
    "name": "Fame",
    "country": "cn"
  },
  {
    "rank": 16,
    "name": "11",
    "country": "mn"
  },
  {
    "rank": 17,
    "name": "GARBAGE",
    "country": "ba"
  },
  {
    "rank": 18,
    "name": "lewis",
    "country": "al"
  },
  {
    "rank": 19,
    "name": "Akashi",
    "team_id": 10020555,
    "team_tag": "PlayTime",
    "country": "ph"
  },
  {
    "rank": 20,
    "name": "Straight Edge",
    "country": "id"
  },
  {
    "rank": 21,
    "name": "shiro",
    "country": "cn"
  },
  {
    "rank": 22,
    "name": "Anya",
    "country": "my"
  },
  {
    "rank": 23,
    "name": "Rupido",
    "team_id": 9879852,
    "team_tag": "Ivory",
    "country": "ph"
  },
  {
    "rank": 24,
    "name": "ponyo",
    "country": "my"
  },
  {
    "rank": 25,
    "name": "Denzsanity"
  },
  {
    "rank": 25,
    "name": "乄Escanor",
    "team_id": 7440699,
    "team_tag": "TSDS",
    "country": "cn"
  },
  {
    "rank": 27,
    "name": "Fbz",
    "team_id": 9828897,
    "team_tag": "RKX",
    "country": "id"
  },
  {
    "rank": 28,
    "name": "do6",
    "country": "th"
  },
  {
    "rank": 29,
    "name": "6"
  },
  {
    "rank": 30,
    "name": "逆"
  },
  {
    "rank": 31,
    "name": "Echozz",
    "team_id": 9640842,
    "team_tag": "TT",
    "country": "cn"
  },
  {
    "rank": 32,
    "name": "Azura",
    "country": "id"
  },
  {
    "rank": 33,
    "name": "Cije",
    "team_id": 9865903,
    "team_tag": "VRJ",
    "country": "id"
  },
  {
    "rank": 34,
    "name": "dalul",
    "team_id": 9828897,
    "team_tag": "RKX",
    "country": "id"
  },
  {
    "rank": 35,
    "name": "MamangDaya",
    "country": "id"
  },
  {
    "rank": 36,
    "name": "Kaiser~",
    "country": "mn"
  },
  {
    "rank": 37,
    "name": "晨"
  },
  {
    "rank": 38,
    "name": "Beyond",
    "country": "cn"
  },
  {
    "rank": 39,
    "name": "Yowe",
    "team_id": 2108395,
    "team_tag": "TNC"
  },
  {
    "rank": 40,
    "name": "Aizen神"
  },
  {
    "rank": 41,
    "name": "raven",
    "country": "ph"
  },
  {
    "rank": 42,
    "name": "Yona"
  },
  {
    "rank": 43,
    "name": "jedd",
    "team_id": 7917893,
    "team_tag": "IAP"
  },
  {
    "rank": 44,
    "name": "Moncleur",
    "country": "id"
  },
  {
    "rank": 45,
    "name": "barlo",
    "country": "al"
  },
  {
    "rank": 46,
    "name": "Kotone"
  },
  {
    "rank": 47,
    "name": "bombi",
    "team_id": 8360138,
    "team_tag": "neon",
    "country": "vn"
  },
  {
    "rank": 48,
    "name": "bowser"
  },
  {
    "rank": 49,
    "name": "怠け者",
    "country": "jp"
  },
  {
    "rank": 50,
    "name": "Wonder’boy",
    "country": "my"
  },
  {
    "rank": 51,
    "name": "Akita",
    "team_id": 9879852,
    "team_tag": "Ivory",
    "country": "ph"
  },
  {
    "rank": 51,
    "name": "PlayHard-",
    "country": "ph"
  },
  {
    "rank": 53,
    "name": "Dust",
    "country": "cn"
  },
  {
    "rank": 54,
    "name": "八追破头流"
  },
  {
    "rank": 55,
    "name": "Nevermine",
    "country": "la"
  },
  {
    "rank": 56,
    "name": "zhadanren_1"
  },
  {
    "rank": 57,
    "name": "Ice Coke❥",
    "country": "cn"
  },
  {
    "rank": 58,
    "name": "zzq"
  },
  {
    "rank": 59,
    "name": "Mao",
    "country": "ar"
  },
  {
    "rank": 60,
    "name": "Haw",
    "country": "al"
  },
  {
    "rank": 61,
    "name": "Autobot"
  },
  {
    "rank": 62,
    "name": "Ren",
    "country": "ph"
  },
  {
    "rank": 63,
    "name": "Hara"
  },
  {
    "rank": 64,
    "name": "wowwwww",
    "country": "ar"
  },
  {
    "rank": 65,
    "name": "Myut",
    "country": "ph"
  },
  {
    "rank": 65,
    "name": "suspect X"
  },
  {
    "rank": 67,
    "name": "Kuku^",
    "team_id": 10020555,
    "team_tag": "PlayTime",
    "country": "ph"
  },
  {
    "rank": 68,
    "name": "afa",
    "team_id": 9699158,
    "team_tag": "TT"
  },
  {
    "rank": 69,
    "name": "jwl"
  },
  {
    "rank": 70,
    "name": "BuHao",
    "team_id": 9865903,
    "team_tag": "VRJ",
    "country": "id"
  },
  {
    "rank": 71,
    "name": "zawrain",
    "country": "io"
  },
  {
    "rank": 72,
    "name": "vtFαded",
    "team_id": 8571960,
    "team_tag": "Orca",
    "country": "my"
  },
  {
    "rank": 73,
    "name": "Shanks",
    "team_id": 8254145,
    "team_tag": "XctN",
    "country": "af"
  },
  {
    "rank": 74,
    "name": "Mnz",
    "country": "in"
  },
  {
    "rank": 75,
    "name": " 1"
  },
  {
    "rank": 76,
    "name": "Blu",
    "country": "ph"
  },
  {
    "rank": 77,
    "name": "Tino",
    "team_id": 8254145,
    "team_tag": "XctN",
    "country": "ph"
  },
  {
    "rank": 78,
    "name": "Ackerman"
  },
  {
    "rank": 79,
    "name": "JFP"
  },
  {
    "rank": 80,
    "name": "     ",
    "team_id": 9323905,
    "team_tag": ""
  },
  {
    "rank": 81,
    "name": "Nse",
    "country": "ph"
  },
  {
    "rank": 82,
    "name": "lulu",
    "country": "cn"
  },
  {
    "rank": 83,
    "name": "BEEBIE",
    "country": "la"
  },
  {
    "rank": 84,
    "name": "FK OFF"
  },
  {
    "rank": 85,
    "name": "THE KING IN THE NORTH",
    "country": "th"
  },
  {
    "rank": 86,
    "name": "womy",
    "team_id": 9865903,
    "team_tag": "VRJ",
    "country": "id"
  },
  {
    "rank": 87,
    "name": "jotun",
    "country": "ph"
  },
  {
    "rank": 88,
    "name": "Killua"
  },
  {
    "rank": 89,
    "name": "Ana",
    "team_id": 9798507,
    "team_tag": "OG"
  },
  {
    "rank": 90,
    "name": "抖音谢乐zzz张泽中",
    "country": "cn"
  },
  {
    "rank": 91,
    "name": "z3",
    "team_id": 10047487,
    "team_tag": "ESS",
    "country": "af"
  },
  {
    "rank": 92,
    "name": "Moomin"
  },
  {
    "rank": 93,
    "name": "V",
    "team_id": 7917893,
    "team_tag": "IAP",
    "country": "ph"
  },
  {
    "rank": 94,
    "name": "kode",
    "country": "id"
  },
  {
    "rank": 95,
    "name": "Varizh",
    "team_id": 9828897,
    "team_tag": "RKX",
    "country": "id"
  },
  {
    "rank": 96,
    "name": "BuryTheHatchet",
    "country": "be"
  },
  {
    "rank": 97,
    "name": "00",
    "country": "ag"
  },
  {
    "rank": 98,
    "name": "Airgetlam",
    "country": "ph"
  },
  {
    "rank": 99,
    "name": "Z",
    "country": "cn"
  },
  {
    "rank": 100,
    "name": "Exx",
    "team_id": 8204917,
    "team_tag": "",
    "country": "cn"
  },
  {
    "rank": 101,
    "name": "Siulung-"
  },
  {
    "rank": 102,
    "name": "KNP",
    "country": "th"
  },
  {
    "rank": 103,
    "name": "Abeng-"
  },
  {
    "rank": 104,
    "name": "roddgeee,",
    "country": "my"
  },
  {
    "rank": 105,
    "name": "MOMO"
  },
  {
    "rank": 106,
    "name": "areuhappy?",
    "country": "id"
  },
  {
    "rank": 107,
    "name": "Yumeyume-",
    "team_id": 9886289,
    "team_tag": ""
  },
  {
    "rank": 108,
    "name": "Earl",
    "country": "ph"
  },
  {
    "rank": 108,
    "name": "mangorose",
    "country": "my"
  },
  {
    "rank": 110,
    "name": "zzq",
    "team_id": 9699158,
    "team_tag": "TT"
  },
  {
    "rank": 111,
    "name": "ANEMONE"
  },
  {
    "rank": 112,
    "name": "kupal",
    "country": "dz"
  },
  {
    "rank": 113,
    "name": "Ma",
    "team_id": 9316973,
    "team_tag": ""
  },
  {
    "rank": 114,
    "name": "Erice",
    "country": "ph"
  },
  {
    "rank": 115,
    "name": "FoL"
  },
  {
    "rank": 116,
    "name": "cinnamoroll"
  },
  {
    "rank": 117,
    "name": "Cr@SH",
    "country": "af"
  },
  {
    "rank": 118,
    "name": "Karl",
    "team_id": 9247085,
    "team_tag": "747"
  },
  {
    "rank": 119,
    "name": "RedNTP",
    "country": "vn"
  },
  {
    "rank": 120,
    "name": "Sword",
    "team_id": 4815445,
    "team_tag": "",
    "country": "ph"
  },
  {
    "rank": 121,
    "name": "无聊的",
    "country": "ax"
  },
  {
    "rank": 122,
    "name": "Epsilon"
  },
  {
    "rank": 123,
    "name": "Kmcn"
  },
  {
    "rank": 124,
    "name": "Yellow Flash of the Leaf",
    "country": "af"
  },
  {
    "rank": 125,
    "name": "mid"
  },
  {
    "rank": 126,
    "name": "Juju",
    "team_id": 9865903,
    "team_tag": "VRJ",
    "country": "af"
  },
  {
    "rank": 127,
    "name": "Rusman-",
    "team_id": 7136526,
    "team_tag": "WOLF",
    "country": "id"
  },
  {
    "rank": 128,
    "name": "yqe"
  },
  {
    "rank": 129,
    "name": "Jinro",
    "team_id": 9449598,
    "team_tag": "lft"
  },
  {
    "rank": 130,
    "name": "オナニストになりたい"
  },
  {
    "rank": 131,
    "name": "黄诗扶"
  },
  {
    "rank": 132,
    "name": "Kokz",
    "team_id": 2108395,
    "team_tag": "TNC",
    "country": "ph"
  },
  {
    "rank": 133,
    "name": "chickenn",
    "country": "au"
  },
  {
    "rank": 134,
    "name": "1tachi-",
    "country": "ax"
  },
  {
    "rank": 135,
    "name": "Qui",
    "team_id": 9600191,
    "team_tag": "GRMFY",
    "country": "ph"
  },
  {
    "rank": 136,
    "name": "-",
    "country": "my"
  },
  {
    "rank": 137,
    "name": "Toy",
    "team_id": 8944573,
    "team_tag": "Reaper"
  },
  {
    "rank": 138,
    "name": "M-Trang.int"
  },
  {
    "rank": 139,
    "name": "Kimizu",
    "country": "ph"
  },
  {
    "rank": 140,
    "name": "Aceaceace"
  },
  {
    "rank": 141,
    "name": "这都拿不下你?"
  },
  {
    "rank": 142,
    "name": "DJ",
    "team_id": 10020555,
    "team_tag": "PlayTime",
    "country": "ph"
  },
  {
    "rank": 143,
    "name": "SabeRNight-"
  },
  {
    "rank": 144,
    "name": "Skill Lay"
  },
  {
    "rank": 145,
    "name": "сгнивший"
  },
  {
    "rank": 146,
    "name": "seen",
    "country": "kr"
  },
  {
    "rank": 147,
    "name": "oiii unlick"
  },
  {
    "rank": 148,
    "name": "LUN"
  },
  {
    "rank": 149,
    "name": "ashness"
  },
  {
    "rank": 150,
    "name": "OBSESSED"
  },
  {
    "rank": 151,
    "name": "trackwer"
  },
  {
    "rank": 152,
    "name": "ChovyY"
  },
  {
    "rank": 153,
    "name": "eon",
    "team_id": 9885928,
    "team_tag": "THR"
  },
  {
    "rank": 154,
    "name": "ireliabroken"
  },
  {
    "rank": 155,
    "name": "midpig",
    "team_id": 9073394,
    "team_tag": "Soy",
    "country": "au"
  },
  {
    "rank": 156,
    "name": "Jy",
    "team_id": 9886289,
    "team_tag": "",
    "country": "my"
  },
  {
    "rank": 157,
    "name": "lzk"
  },
  {
    "rank": 158,
    "name": "ivan",
    "country": "ph"
  },
  {
    "rank": 159,
    "name": ")"
  },
  {
    "rank": 160,
    "name": "loysueuuu",
    "team_id": 9041358,
    "team_tag": "123"
  },
  {
    "rank": 161,
    "name": "Setsu",
    "country": "cn"
  },
  {
    "rank": 162,
    "name": "gaven"
  },
  {
    "rank": 163,
    "name": "FUN"
  },
  {
    "rank": 164,
    "name": "arabica"
  },
  {
    "rank": 165,
    "name": "Nine Nz"
  },
  {
    "rank": 166,
    "name": "ramadan"
  },
  {
    "rank": 167,
    "name": "barsulan"
  },
  {
    "rank": 168,
    "name": "geO`",
    "country": "ua"
  },
  {
    "rank": 169,
    "name": "Sy",
    "country": "af"
  },
  {
    "rank": 170,
    "name": "CKY",
    "country": "my"
  },
  {
    "rank": 171,
    "name": "iBmaN",
    "country": "af"
  },
  {
    "rank": 172,
    "name": "Raiden"
  },
  {
    "rank": 173,
    "name": "Tomoe"
  },
  {
    "rank": 174,
    "name": "Lyracelt",
    "team_id": 9389051,
    "team_tag": ""
  },
  {
    "rank": 175,
    "name": "130",
    "country": "cn"
  },
  {
    "rank": 176,
    "name": "Boombui",
    "team_id": 9586396,
    "team_tag": "Xuou",
    "country": "th"
  },
  {
    "rank": 177,
    "name": "nvd^^"
  },
  {
    "rank": 178,
    "name": "õ_ó",
    "team_id": 8329831,
    "team_tag": "",
    "country": "ax"
  },
  {
    "rank": 179,
    "name": "剑来！",
    "country": "cn"
  },
  {
    "rank": 180,
    "name": "dnm ",
    "country": "au"
  },
  {
    "rank": 181,
    "name": "月亮战士"
  },
  {
    "rank": 182,
    "name": "dff",
    "team_id": 8076985,
    "team_tag": ""
  },
  {
    "rank": 183,
    "name": "Bok"
  },
  {
    "rank": 184,
    "name": "Kwa",
    "team_id": 9239009,
    "team_tag": "",
    "country": "mn"
  },
  {
    "rank": 185,
    "name": "K"
  },
  {
    "rank": 186,
    "name": "="
  },
  {
    "rank": 187,
    "name": "Steinz",
    "team_id": 8911648,
    "team_tag": "439TMRR",
    "country": "th"
  },
  {
    "rank": 188,
    "name": "Marisa"
  },
  {
    "rank": 189,
    "name": "QWER",
    "team_id": 3326126,
    "team_tag": "VG.J",
    "country": "cn"
  },
  {
    "rank": 190,
    "name": "石中剑"
  },
  {
    "rank": 191,
    "name": "Maps"
  },
  {
    "rank": 192,
    "name": "Jarim",
    "country": "id"
  },
  {
    "rank": 193,
    "name": "blue"
  },
  {
    "rank": 194,
    "name": "Dang3r",
    "country": "my"
  },
  {
    "rank": 195,
    "name": "่"
  },
  {
    "rank": 196,
    "name": "gilticus"
  },
  {
    "rank": 197,
    "name": "圣子华炼GODKING -"
  },
  {
    "rank": 198,
    "name": "NotJammel_1",
    "country": "ph"
  },
  {
    "rank": 199,
    "name": "merciful",
    "country": "id"
  },
  {
    "rank": 200,
    "name": "0 iq player",
    "team_id": 9742225,
    "team_tag": "",
    "country": "ph"
  },
  {
    "rank": 200,
    "name": "giroha",
    "country": "ph"
  },
  {
    "rank": 202,
    "name": "bilibili.肉夹馍",
    "team_id": 9717978,
    "team_tag": "bilibili"
  },
  {
    "rank": 203,
    "name": "ilaan",
    "country": "ph"
  },
  {
    "rank": 204,
    "name": "ingrid"
  },
  {
    "rank": 205,
    "name": "爆浆麻薯",
    "team_id": 8769415,
    "team_tag": "bili",
    "country": "cn"
  },
  {
    "rank": 206,
    "name": "跨越障碍吧！"
  },
  {
    "rank": 207,
    "name": "OracleBCD",
    "country": "ph"
  },
  {
    "rank": 207,
    "name": "路遥"
  },
  {
    "rank": 209,
    "name": "luckylife",
    "team_id": 8451977,
    "team_tag": ""
  },
  {
    "rank": 210,
    "name": "Pakazs"
  },
  {
    "rank": 211,
    "name": "xinmakui"
  },
  {
    "rank": 212,
    "name": "NELEL"
  },
  {
    "rank": 212,
    "name": "Chucky",
    "country": "my"
  },
  {
    "rank": 214,
    "name": "孤星寥落"
  },
  {
    "rank": 215,
    "name": "She no reply :("
  },
  {
    "rank": 216,
    "name": "Orochi"
  },
  {
    "rank": 217,
    "name": "Agressif",
    "team_id": 2777247,
    "team_tag": ""
  },
  {
    "rank": 218,
    "name": "ogyrec"
  },
  {
    "rank": 219,
    "name": "SHYNES$BOY",
    "country": "cn"
  },
  {
    "rank": 220,
    "name": "tomatoes"
  },
  {
    "rank": 221,
    "name": "Himmel"
  },
  {
    "rank": 222,
    "name": "Nov.",
    "team_id": 9425949,
    "team_tag": "11",
    "country": "cn"
  },
  {
    "rank": 223,
    "name": "youc",
    "country": "cn"
  },
  {
    "rank": 224,
    "name": "simka"
  },
  {
    "rank": 225,
    "name": "HANBAO",
    "team_id": 7489019,
    "team_tag": ""
  },
  {
    "rank": 226,
    "name": "zoro"
  },
  {
    "rank": 227,
    "name": "hanka"
  },
  {
    "rank": 228,
    "name": "Sonny"
  },
  {
    "rank": 229,
    "name": "Scz"
  },
  {
    "rank": 230,
    "name": "DazaM",
    "team_id": 8588909,
    "team_tag": "",
    "country": "id"
  },
  {
    "rank": 231,
    "name": "42",
    "country": "cn"
  },
  {
    "rank": 232,
    "name": "day6.3"
  },
  {
    "rank": 233,
    "name": "狗脑",
    "team_id": 9717046,
    "team_tag": "",
    "country": "ph"
  },
  {
    "rank": 234,
    "name": "l1ght"
  },
  {
    "rank": 235,
    "name": "Ateeeeeeeee"
  },
  {
    "rank": 236,
    "name": "D-L a s t"
  },
  {
    "rank": 237,
    "name": "Asgold"
  },
  {
    "rank": 238,
    "name": "Isa"
  },
  {
    "rank": 238,
    "name": "DaddyC"
  },
  {
    "rank": 240,
    "name": "万与啊"
  },
  {
    "rank": 241,
    "name": "萨斯拉"
  },
  {
    "rank": 242,
    "name": "Matt-Ü",
    "country": "jp"
  },
  {
    "rank": 243,
    "name": "notilt"
  },
  {
    "rank": 244,
    "name": "ok林仔"
  },
  {
    "rank": 245,
    "name": "zxcus"
  },
  {
    "rank": 246,
    "name": "Ares"
  },
  {
    "rank": 247,
    "name": "Kaine"
  },
  {
    "rank": 248,
    "name": "Too much pressure"
  },
  {
    "rank": 249,
    "name": "mir",
    "country": "my"
  },
  {
    "rank": 250,
    "name": "Eze",
    "team_id": 8910919,
    "team_tag": ""
  },
  {
    "rank": 251,
    "name": "Kunaka"
  },
  {
    "rank": 252,
    "name": "LaVine",
    "team_id": 2354560,
    "team_tag": "",
    "country": "hk"
  },
  {
    "rank": 253,
    "name": "Unwelcome School"
  },
  {
    "rank": 254,
    "name": "jia",
    "country": "sg"
  },
  {
    "rank": 255,
    "name": "Drew",
    "country": "id"
  },
  {
    "rank": 256,
    "name": "Klein"
  },
  {
    "rank": 257,
    "name": "Nichijou - Mio",
    "country": "vn"
  },
  {
    "rank": 258,
    "name": " Tira. ",
    "team_id": 7485853,
    "team_tag": ""
  },
  {
    "rank": 259,
    "name": "dangaroo",
    "country": "my"
  },
  {
    "rank": 260,
    "name": "RomanticLust",
    "team_id": 9717565,
    "team_tag": "",
    "country": "id"
  },
  {
    "rank": 261,
    "name": "胖胖大王"
  },
  {
    "rank": 262,
    "name": "`JL",
    "country": "ph"
  },
  {
    "rank": 263,
    "name": "Chaos"
  },
  {
    "rank": 264,
    "name": "egor nightfall grigorenko",
    "team_id": 9819408,
    "team_tag": "Tuku",
    "country": "ag"
  },
  {
    "rank": 265,
    "name": "yO2",
    "country": "th"
  },
  {
    "rank": 266,
    "name": "chunga"
  },
  {
    "rank": 266,
    "name": "肥猪宝驾到统统闪开"
  },
  {
    "rank": 268,
    "name": "MUGG"
  },
  {
    "rank": 269,
    "name": "^",
    "team_id": 8089865,
    "team_tag": "150B",
    "country": "ph"
  },
  {
    "rank": 270,
    "name": "|₮|—",
    "country": "ph"
  },
  {
    "rank": 271,
    "name": "ZSMJ",
    "country": "cn"
  },
  {
    "rank": 272,
    "name": "我的队友为何布朗运动",
    "team_id": 5970048,
    "team_tag": "THU",
    "country": "cn"
  },
  {
    "rank": 273,
    "name": "Kiminoto",
    "team_id": 4152234,
    "team_tag": ""
  },
  {
    "rank": 274,
    "name": "Unfinished"
  },
  {
    "rank": 275,
    "name": "吟游诗人",
    "country": "cn"
  },
  {
    "rank": 276,
    "name": "asdsaddsds"
  },
  {
    "rank": 276,
    "name": "Invictus",
    "team_id": 2800161,
    "team_tag": "DC",
    "country": "cn"
  },
  {
    "rank": 278,
    "name": "Vertigo",
    "country": "sg"
  },
  {
    "rank": 279,
    "name": "ASU"
  },
  {
    "rank": 280,
    "name": "ann ann",
    "country": "th"
  },
  {
    "rank": 281,
    "name": "matrix",
    "country": "lk"
  },
  {
    "rank": 282,
    "name": " ",
    "country": "ru"
  },
  {
    "rank": 283,
    "name": "DarrkMen"
  },
  {
    "rank": 284,
    "name": "Rin"
  },
  {
    "rank": 285,
    "name": "Patlatius"
  },
  {
    "rank": 286,
    "name": "tv/sess1a LFT.pos3",
    "country": "dz"
  },
  {
    "rank": 287,
    "name": "sosa ",
    "team_id": 9724060,
    "team_tag": "AAAA",
    "country": "cr"
  },
  {
    "rank": 288,
    "name": "Dream丶Future"
  },
  {
    "rank": 289,
    "name": "PTa（找队）"
  },
  {
    "rank": 290,
    "name": "Theseus"
  },
  {
    "rank": 291,
    "name": "笨蛋猪"
  },
  {
    "rank": 292,
    "name": "t8om-"
  },
  {
    "rank": 292,
    "name": "别来无恙."
  },
  {
    "rank": 294,
    "name": "aavreil"
  },
  {
    "rank": 295,
    "name": "B"
  },
  {
    "rank": 296,
    "name": "Xokep"
  },
  {
    "rank": 297,
    "name": "Marin"
  },
  {
    "rank": 298,
    "name": "nanodesu"
  },
  {
    "rank": 299,
    "name": "Kobe神",
    "country": "ph"
  },
  {
    "rank": 300,
    "name": "Emotional damage :("
  },
  {
    "rank": 301,
    "name": "ENJOY"
  },
  {
    "rank": 302,
    "name": "Equinox",
    "country": "id"
  },
  {
    "rank": 303,
    "name": "trusted"
  },
  {
    "rank": 304,
    "name": "杰斯琳  - BAHLIL GARIS KERAS"
  },
  {
    "rank": 305,
    "name": "退役男大过上慢生活"
  },
  {
    "rank": 306,
    "name": "DD"
  },
  {
    "rank": 307,
    "name": "blacklocked",
    "team_id": 5161268,
    "team_tag": "EvlInc",
    "country": "in"
  },
  {
    "rank": 308,
    "name": "Fate",
    "team_id": 9180464,
    "team_tag": "TC",
    "country": "bd"
  },
  {
    "rank": 309,
    "name": "Skye",
    "country": "ph"
  },
  {
    "rank": 310,
    "name": "Splicko",
    "country": "au"
  },
  {
    "rank": 311,
    "name": "红烧于哥",
    "team_id": 2877131,
    "team_tag": "",
    "country": "cn"
  },
  {
    "rank": 312,
    "name": "meow",
    "country": "np"
  },
  {
    "rank": 313,
    "name": "Roman-",
    "country": "pr"
  },
  {
    "rank": 314,
    "name": "逗哥一笑"
  },
  {
    "rank": 315,
    "name": "菁"
  },
  {
    "rank": 316,
    "name": "Dota2蛋挞"
  },
  {
    "rank": 317,
    "name": "白眼狼王dyw"
  },
  {
    "rank": 318,
    "name": "Yatoro",
    "team_id": 9454765,
    "team_tag": ""
  },
  {
    "rank": 319,
    "name": "BIC"
  },
  {
    "rank": 320,
    "name": "閃光のハサウェイ",
    "team_id": 9801121,
    "team_tag": "",
    "country": "cn"
  },
  {
    "rank": 321,
    "name": "MungKrush"
  },
  {
    "rank": 322,
    "name": "Dr.Mani",
    "team_id": 9224514,
    "team_tag": ""
  },
  {
    "rank": 323,
    "name": "高手坟墓"
  },
  {
    "rank": 324,
    "name": "Traf"
  },
  {
    "rank": 325,
    "name": "Gloke",
    "country": "sg"
  },
  {
    "rank": 326,
    "name": "QWER",
    "team_id": 10074748,
    "team_tag": "VG.J",
    "country": "th"
  },
  {
    "rank": 327,
    "name": "Sup player (PMA)"
  },
  {
    "rank": 328,
    "name": "。"
  },
  {
    "rank": 329,
    "name": "Cassie",
    "team_id": 9717155,
    "team_tag": "DDS",
    "country": "kh"
  },
  {
    "rank": 330,
    "name": " ",
    "country": "my"
  },
  {
    "rank": 331,
    "name": "kami"
  },
  {
    "rank": 332,
    "name": "Broken/M1rror7",
    "team_id": 9018770,
    "team_tag": "RKZ",
    "country": "ru"
  },
  {
    "rank": 332,
    "name": "poomkin"
  },
  {
    "rank": 334,
    "name": "Wizard",
    "team_id": 9766159,
    "team_tag": "."
  },
  {
    "rank": 335,
    "name": "мусор",
    "country": "cm"
  },
  {
    "rank": 336,
    "name": "ZoZoZo"
  },
  {
    "rank": 337,
    "name": "Lemon."
  },
  {
    "rank": 338,
    "name": "S"
  },
  {
    "rank": 339,
    "name": "星街すいせい",
    "country": "cn"
  },
  {
    "rank": 340,
    "name": "不灭羽",
    "team_id": 1847880,
    "team_tag": ""
  },
  {
    "rank": 341,
    "name": "1123..",
    "country": "ag"
  },
  {
    "rank": 342,
    "name": "Xin",
    "team_id": 9518289,
    "team_tag": "5D"
  },
  {
    "rank": 343,
    "name": "my reflection"
  },
  {
    "rank": 344,
    "name": "skadoosh",
    "country": "id"
  },
  {
    "rank": 345,
    "name": "PhaeBin"
  },
  {
    "rank": 346,
    "name": "泥～，泥啪～☆"
  },
  {
    "rank": 347,
    "name": "bemyself"
  },
  {
    "rank": 348,
    "name": "Alex",
    "country": "cn"
  },
  {
    "rank": 349,
    "name": "BARK",
    "team_id": 9717115,
    "team_tag": "",
    "country": "ph"
  },
  {
    "rank": 350,
    "name": "小黑"
  },
  {
    "rank": 351,
    "name": "回音如果",
    "country": "cn"
  },
  {
    "rank": 352,
    "name": "放逐之刃"
  },
  {
    "rank": 353,
    "name": "wtf man",
    "country": "ph"
  },
  {
    "rank": 354,
    "name": "hello world"
  },
  {
    "rank": 354,
    "name": "Nichijou",
    "country": "vn"
  },
  {
    "rank": 356,
    "name": "Kaisora",
    "country": "id"
  },
  {
    "rank": 357,
    "name": "Tigger",
    "country": "th"
  },
  {
    "rank": 358,
    "name": "小火",
    "team_id": 9735373,
    "team_tag": ""
  },
  {
    "rank": 358,
    "name": "gangster"
  },
  {
    "rank": 360,
    "name": "GokinG"
  },
  {
    "rank": 361,
    "name": "D-",
    "team_id": 7036430,
    "team_tag": "NSG",
    "country": "cn"
  },
  {
    "rank": 362,
    "name": "Kyrix-",
    "team_id": 3692459,
    "team_tag": "WW",
    "country": "mn"
  },
  {
    "rank": 363,
    "name": "C"
  },
  {
    "rank": 364,
    "name": "example"
  },
  {
    "rank": 365,
    "name": "急先锋"
  },
  {
    "rank": 366,
    "name": "Lord",
    "country": "mn"
  },
  {
    "rank": 366,
    "name": "CityBoy",
    "team_id": 9799418,
    "team_tag": "",
    "country": "cn"
  },
  {
    "rank": 368,
    "name": "Habibi"
  },
  {
    "rank": 369,
    "name": "e m o b o y",
    "country": "vn"
  },
  {
    "rank": 370,
    "name": "我妻由乃"
  },
  {
    "rank": 371,
    "name": "Bleys",
    "country": "jp"
  },
  {
    "rank": 372,
    "name": "Yasa"
  },
  {
    "rank": 373,
    "name": "KULAONG",
    "country": "dz"
  },
  {
    "rank": 374,
    "name": "pisteng yawaka",
    "country": "bj"
  },
  {
    "rank": 375,
    "name": "Co2"
  },
  {
    "rank": 376,
    "name": "N9shot"
  },
  {
    "rank": 377,
    "name": "agent"
  },
  {
    "rank": 378,
    "name": "XER"
  },
  {
    "rank": 379,
    "name": "33babe",
    "team_id": 9972680,
    "team_tag": "Ave Mujica",
    "country": "cn"
  },
  {
    "rank": 380,
    "name": "carina",
    "team_id": 9382173,
    "team_tag": "キミの記憶",
    "country": "sg"
  },
  {
    "rank": 381,
    "name": "Stylist",
    "country": "th"
  },
  {
    "rank": 382,
    "name": "Rumor"
  },
  {
    "rank": 383,
    "name": "lun0s"
  },
  {
    "rank": 384,
    "name": "Uchiha Sasuke"
  },
  {
    "rank": 385,
    "name": "大核 ",
    "country": "cn"
  },
  {
    "rank": 386,
    "name": "Anasas$s"
  },
  {
    "rank": 387,
    "name": "Topson"
  },
  {
    "rank": 388,
    "name": "Nightmare",
    "team_id": 10019949,
    "team_tag": "Hydra"
  },
  {
    "rank": 389,
    "name": "killer123",
    "team_id": 9640753,
    "team_tag": ""
  },
  {
    "rank": 389,
    "name": "SADBOY `",
    "country": "th"
  },
  {
    "rank": 391,
    "name": "Sep",
    "country": "ph"
  },
  {
    "rank": 392,
    "name": "psychological"
  },
  {
    "rank": 393,
    "name": "10 pm (demon time)"
  },
  {
    "rank": 394,
    "name": "Clarkson",
    "team_id": 9410100,
    "team_tag": "FAKGG",
    "country": "cn"
  },
  {
    "rank": 395,
    "name": "云"
  },
  {
    "rank": 396,
    "name": "彬彬鬼"
  },
  {
    "rank": 397,
    "name": "Reader",
    "team_id": 5142890,
    "team_tag": ""
  },
  {
    "rank": 398,
    "name": "Crupil"
  },
  {
    "rank": 398,
    "name": "walangbitawboi"
  },
  {
    "rank": 400,
    "name": "  "
  },
  {
    "rank": 401,
    "name": "zhan"
  },
  {
    "rank": 402,
    "name": "Old Monster🚥",
    "country": "cn"
  },
  {
    "rank": 403,
    "name": "Arushi ",
    "country": "id"
  },
  {
    "rank": 404,
    "name": "Kana-",
    "country": "ph"
  },
  {
    "rank": 405,
    "name": "insomnia@@"
  },
  {
    "rank": 405,
    "name": "Eddie"
  },
  {
    "rank": 407,
    "name": "Riricute",
    "country": "ph"
  },
  {
    "rank": 408,
    "name": "soup",
    "team_id": 8863885,
    "team_tag": "RSA",
    "country": "za"
  },
  {
    "rank": 409,
    "name": "踊り子"
  },
  {
    "rank": 410,
    "name": "กาแฟ",
    "team_id": 8399965,
    "team_tag": "",
    "country": "th"
  },
  {
    "rank": 411,
    "name": "IO"
  },
  {
    "rank": 412,
    "name": "Ah Minuk"
  },
  {
    "rank": 413,
    "name": "狗头军师"
  },
  {
    "rank": 414,
    "name": "sky",
    "team_id": 2565026,
    "team_tag": "3H",
    "country": "cn"
  },
  {
    "rank": 415,
    "name": "I v a n"
  },
  {
    "rank": 415,
    "name": "哈尔"
  },
  {
    "rank": 417,
    "name": "Bene",
    "team_id": 3352867,
    "team_tag": "",
    "country": "ph"
  },
  {
    "rank": 418,
    "name": "saviour",
    "country": "ph"
  },
  {
    "rank": 418,
    "name": "猴子全是哈哈怪"
  },
  {
    "rank": 420,
    "name": "Rain",
    "team_id": 9705630,
    "team_tag": ""
  },
  {
    "rank": 421,
    "name": "Justus"
  },
  {
    "rank": 422,
    "name": "PMA?"
  },
  {
    "rank": 423,
    "name": "ゅ",
    "team_id": 9434126,
    "team_tag": ""
  },
  {
    "rank": 424,
    "name": "Ruby",
    "team_id": 9735236,
    "team_tag": "",
    "country": "cn"
  },
  {
    "rank": 425,
    "name": "Brish2",
    "team_id": 5835106,
    "team_tag": ".",
    "country": "ai"
  },
  {
    "rank": 426,
    "name": "Less",
    "team_id": 9671002,
    "team_tag": "PNQ",
    "country": "ph"
  },
  {
    "rank": 427,
    "name": "Tiktok:Le Duc Trung transformers"
  },
  {
    "rank": 428,
    "name": "Chalice"
  },
  {
    "rank": 428,
    "name": "Kody",
    "team_id": 9793022,
    "team_tag": "scug",
    "country": "au"
  },
  {
    "rank": 430,
    "name": "R"
  },
  {
    "rank": 431,
    "name": "Seven",
    "country": "cn"
  },
  {
    "rank": 431,
    "name": "Neo",
    "team_id": 7203103,
    "team_tag": "",
    "country": "mn"
  },
  {
    "rank": 433,
    "name": "KONTRABIDA pos5",
    "team_id": 8299983,
    "team_tag": "SZG",
    "country": "ru"
  },
  {
    "rank": 433,
    "name": "Tpyy",
    "country": "ph"
  },
  {
    "rank": 435,
    "name": "无敌小鱼大王"
  },
  {
    "rank": 436,
    "name": "Ferd"
  },
  {
    "rank": 437,
    "name": "小星星"
  },
  {
    "rank": 438,
    "name": "90977",
    "country": "bz"
  },
  {
    "rank": 439,
    "name": "wufan"
  },
  {
    "rank": 440,
    "name": "Jerax Prime",
    "country": "sg"
  },
  {
    "rank": 441,
    "name": "8 no way!!"
  },
  {
    "rank": 442,
    "name": "我的刀盾"
  },
  {
    "rank": 443,
    "name": "WTW"
  },
  {
    "rank": 443,
    "name": "s-"
  },
  {
    "rank": 445,
    "name": "斌 ",
    "country": "cn"
  },
  {
    "rank": 446,
    "name": "散仙",
    "country": "cn"
  },
  {
    "rank": 447,
    "name": "zzz",
    "country": "ag"
  },
  {
    "rank": 447,
    "name": "SFDondo"
  },
  {
    "rank": 449,
    "name": "你受的是什么教育",
    "country": "cn"
  },
  {
    "rank": 450,
    "name": "Perdiks"
  },
  {
    "rank": 451,
    "name": "chiiiy"
  },
  {
    "rank": 452,
    "name": "catgwah",
    "team_id": 5768614,
    "team_tag": "CHOMP",
    "country": "au"
  },
  {
    "rank": 453,
    "name": "messi"
  },
  {
    "rank": 453,
    "name": "Paring",
    "team_id": 9799284,
    "team_tag": "CC",
    "country": "ph"
  },
  {
    "rank": 453,
    "name": "Mezz*"
  },
  {
    "rank": 453,
    "name": "Emperor Len",
    "team_id": 8713367,
    "team_tag": "V36",
    "country": "bd"
  },
  {
    "rank": 457,
    "name": "Serendipity"
  },
  {
    "rank": 457,
    "name": "Revolution",
    "country": "af"
  },
  {
    "rank": 459,
    "name": "deyuuum-",
    "team_id": 9838831,
    "team_tag": ""
  },
  {
    "rank": 460,
    "name": ".",
    "team_id": 9804562,
    "team_tag": "."
  },
  {
    "rank": 461,
    "name": "Dheart"
  },
  {
    "rank": 462,
    "name": "Kusaka Masato"
  },
  {
    "rank": 462,
    "name": "古月方源"
  },
  {
    "rank": 464,
    "name": "ANDREI666"
  },
  {
    "rank": 465,
    "name": "ShockArrow",
    "team_id": 8476887,
    "team_tag": "wmt"
  },
  {
    "rank": 466,
    "name": "Purun"
  },
  {
    "rank": 466,
    "name": "Yuiko",
    "country": "ca"
  },
  {
    "rank": 468,
    "name": "pakpunpak"
  },
  {
    "rank": 469,
    "name": "seyb",
    "country": "ph"
  },
  {
    "rank": 470,
    "name": "village"
  },
  {
    "rank": 471,
    "name": "Bericdondurian"
  },
  {
    "rank": 472,
    "name": "Mothernase"
  },
  {
    "rank": 473,
    "name": "ALu"
  },
  {
    "rank": 474,
    "name": "Lapras",
    "country": "cn"
  },
  {
    "rank": 474,
    "name": "永安赏花",
    "team_id": 6213511,
    "team_tag": "伐",
    "country": "cn"
  },
  {
    "rank": 476,
    "name": "MARCSADDI",
    "team_id": 2396252,
    "team_tag": "SPYSEA",
    "country": "ph"
  },
  {
    "rank": 476,
    "name": "margit",
    "team_id": 3787828,
    "team_tag": "",
    "country": "ph"
  },
  {
    "rank": 478,
    "name": "Jieun",
    "team_id": 9614965,
    "team_tag": "",
    "country": "id"
  },
  {
    "rank": 479,
    "name": "DayIsDone"
  },
  {
    "rank": 480,
    "name": "十万嬉皮"
  },
  {
    "rank": 481,
    "name": "No care",
    "country": "my"
  },
  {
    "rank": 482,
    "name": "-BlackJack-"
  },
  {
    "rank": 483,
    "name": "二等饼干"
  },
  {
    "rank": 484,
    "name": "MODE:TRYHARD"
  },
  {
    "rank": 485,
    "name": "Kenchang",
    "country": "bv"
  },
  {
    "rank": 485,
    "name": "Archmage-",
    "team_id": 8245350,
    "team_tag": "",
    "country": "in"
  },
  {
    "rank": 487,
    "name": "IBAYUE"
  },
  {
    "rank": 488,
    "name": "爱琴海战神"
  },
  {
    "rank": 489,
    "name": "Shishiba",
    "country": "id"
  },
  {
    "rank": 490,
    "name": "Olympic.KoHtay"
  },
  {
    "rank": 490,
    "name": "瞬雷天闪",
    "team_id": 9493051,
    "team_tag": ""
  },
  {
    "rank": 492,
    "name": "Johnny"
  },
  {
    "rank": 493,
    "name": "陆江仙.",
    "country": "cn"
  },
  {
    "rank": 494,
    "name": "a?"
  },
  {
    "rank": 495,
    "name": "Eh"
  },
  {
    "rank": 496,
    "name": "HandsomeJ_",
    "country": "hk"
  },
  {
    "rank": 497,
    "name": "mada",
    "team_id": 2645421,
    "team_tag": "EH",
    "country": "ph"
  },
  {
    "rank": 498,
    "name": "belle",
    "team_id": 8815641,
    "team_tag": "sisterrizz",
    "country": "cn"
  },
  {
    "rank": 499,
    "name": "."
  },
  {
    "rank": 500,
    "name": "Flame`",
    "country": "pk"
  }
]
